{"py/object": "rasa.core.featurizers.tracker_featurizers.MaxHistoryTrackerFeaturizer", "state_featurizer": {"py/object": "rasa.core.featurizers.single_state_featurizer.SingleStateFeaturizer", "_default_feature_states": {"intent": {"academic_calendar": 0, "admission_info": 1, "admission_info_btech": 2, "admission_info_mtech": 3, "admission_info_phd": 4, "back": 5, "contact_info": 6, "events": 7, "exam_info": 8, "facility_info": 9, "facility_info_computer_center": 10, "facility_info_hostel": 11, "facility_info_library": 12, "goodbye": 13, "greeting": 14, "help": 15, "important_dates": 16, "job_openings": 17, "latest_news": 18, "locate_notices": 19, "locate_results": 20, "nlu_fallback": 21, "out_of_scope": 22, "restart": 23, "session_start": 24, "student_welfare": 25, "tender_notices": 26, "thanks": 27, "vision_mission": 28}, "action_name": {"action_listen": 0, "action_restart": 1, "action_session_start": 2, "action_default_fallback": 3, "action_deactivate_loop": 4, "action_revert_fallback_events": 5, "action_default_ask_affirmation": 6, "action_default_ask_rephrase": 7, "action_two_stage_fallback": 8, "action_unlikely_intent": 9, "action_back": 10, "...": 11, "action_extract_slots": 12, "utter_academic_calendar": 13, "utter_admission_info": 14, "utter_admission_info_btech": 15, "utter_admission_info_mtech": 16, "utter_admission_info_phd": 17, "utter_contact_info": 18, "utter_events": 19, "utter_exam_info": 20, "utter_facility_info": 21, "utter_facility_info_computer_center": 22, "utter_facility_info_hostel": 23, "utter_facility_info_library": 24, "utter_goodbye": 25, "utter_greeting": 26, "utter_help": 27, "utter_important_dates": 28, "utter_job_openings": 29, "utter_latest_news": 30, "utter_locate_notices": 31, "utter_locate_results": 32, "utter_student_welfare": 33, "utter_tender_notices": 34, "utter_thanks": 35, "utter_vision_mission": 36}, "entities": {}, "slots": {}, "active_loop": {}}, "action_texts": [], "entity_tag_specs": []}, "max_history": 5, "remove_duplicates": true}